MIMIC_IV_MEDS/__init__.py
MIMIC_IV_MEDS/__main__.py
MIMIC_IV_MEDS/commands.py
MIMIC_IV_MEDS/dataset.yaml
MIMIC_IV_MEDS/download.py
MIMIC_IV_MEDS/pre_MEDS.py
MIMIC_IV_MEDS/configs/ETL.yaml
MIMIC_IV_MEDS/configs/__init__.py
MIMIC_IV_MEDS/configs/event_configs.yaml
MIMIC_IV_MEDS/configs/main.yaml
MIMIC_IV_MEDS/configs/runner.yaml
mimic_iv_meds-0.0.7.dist-info/licenses/LICENSE
mimic_iv_meds-0.0.7.dist-info/METADATA
mimic_iv_meds-0.0.7.dist-info/WHEEL
mimic_iv_meds-0.0.7.dist-info/entry_points.txt
mimic_iv_meds-0.0.7.dist-info/top_level.txt
mimic_iv_meds-0.0.7.dist-info/RECORD
