Metadata-Version: 2.4
Name: MIMIC-IV-MEDS
Version: 0.0.7
Summary: An ETL pipeline to extract MIMIC-IV data into the MEDS format.
Author-email: Matthew McDermott <mattmcdermott8@gmail.com>
Project-URL: Homepage, https://github.com/Medical-Event-Data-Standard/MIMIC_IV_MEDS
Project-URL: Issues, https://github.com/Medical-Event-Data-Standard/MIMIC_IV_MEDS/issues
Classifier: Programming Language :: Python :: 3
Classifier: License :: OSI Approved :: MIT License
Classifier: Operating System :: OS Independent
Requires-Python: >=3.11
License-File: LICENSE
Requires-Dist: polars>=1.26.0,~=1.27.0
Requires-Dist: meds-transforms~=0.2.1
Requires-Dist: requests
Requires-Dist: beautifulsoup4
Requires-Dist: hydra-core
Provides-Extra: dev
Requires-Dist: pre-commit<4; extra == "dev"
Provides-Extra: tests
Requires-Dist: pytest; extra == "tests"
Requires-Dist: pytest-cov; extra == "tests"
Provides-Extra: local-parallelism
Requires-Dist: hydra-joblib-launcher; extra == "local-parallelism"
Provides-Extra: slurm-parallelism
Requires-Dist: hydra-submitit-launcher; extra == "slurm-parallelism"
Dynamic: license-file
